README.md
setup.cfg
setup.py
nadds/__init__.py
nadds/_tuntap.c
nadds/fchdir.py
nadds/passfd.py
nadds/recvmsg.c
nadds/sendmsg.c
nadds/socket_const.c
nadds/socketpair.c
nadds/tuntap.py
nadds.egg-info/PKG-INFO
nadds.egg-info/SOURCES.txt
nadds.egg-info/dependency_links.txt
nadds.egg-info/top_level.txt