Metadata-Version: 1.1
Name: nadds
Version: 0.1.2
Summary: Low level linux api calls for python
Home-page: https://github.com/orlof/python-nadds/
Author: Orlof
Author-email: orlof@users.noreply.github.com
License: GNU LGPL
Download-URL: https://github.com/orlof/python-nadds/archive/0.1.2.tar.gz
Keywords: python,api
Platform: UNKNOWN
Classifier: Development Status :: 3 - Alpha
Classifier: Intended Audience :: Developers
Classifier: License :: OSI Approved :: GNU Library or Lesser General Public License (LGPL)
Classifier: Operating System :: POSIX :: Linux
Classifier: Programming Language :: Python :: 2.7
Classifier: Programming Language :: Python :: Implementation :: CPython
Classifier: Topic :: Utilities
